farrow_and_ball/__init__.py
farrow_and_ball/palettes.py
farrow_and_ball-0.0.3.dist-info/LICENSE
farrow_and_ball-0.0.3.dist-info/METADATA
farrow_and_ball-0.0.3.dist-info/WHEEL
farrow_and_ball-0.0.3.dist-info/top_level.txt
farrow_and_ball-0.0.3.dist-info/RECORD
