Metadata-Version: 2.1
Name: farrow-and-ball
Version: 0.0.3
Summary: Port of the R farrowandball palette implementation.
Home-page: https://github.com/vork/farrowandball
Author: Mark Boss
Author-email: hello@markboss.me
License: UNKNOWN
Project-URL: Bug Tracker, https://github.com/vork/farrowandball/issues
Project-URL: Source, https://github.com/vork/farrowandball
Keywords: matplotlib,colormap,palette
Platform: UNKNOWN
Classifier: Development Status :: 3 - Alpha
Classifier: Intended Audience :: Developers
Classifier: Programming Language :: Python :: 3
Classifier: License :: OSI Approved :: MIT License
Classifier: Operating System :: OS Independent
Requires-Python: >=3
License-File: LICENSE
Requires-Dist: matplotlib
Requires-Dist: enum34 ; python_version < "3.4"
